scratchcommunication/__init__.py
scratchcommunication/cloud.py
scratchcommunication/cloud_socket.py
scratchcommunication/commons.py
scratchcommunication/exceptions.py
scratchcommunication/py.typed
scratchcommunication/security.py
scratchcommunication/session.py
scratchcommunication/betas/__init__.py
scratchcommunication/betas/poly_cloud.py
scratchcommunication/betas/undo_events.py
scratchcommunication/cloudrequests/__init__.py
scratchcommunication/cloudrequests/basetypes.py
scratchcommunication/cloudrequests/requests.py
scratchcommunication-2.15.6.dist-info/licenses/LICENSE
scratchcommunication-2.15.6.dist-info/METADATA
scratchcommunication-2.15.6.dist-info/WHEEL
scratchcommunication-2.15.6.dist-info/top_level.txt
scratchcommunication-2.15.6.dist-info/RECORD
