Metadata-Version: 2.4
Name: scratchcommunication
Version: 2.15.6
Summary: A python module for communicating with scratch projects
Author: Gine Mosild
Author-email: tcc@thecommcraft.de
Project-URL: Source, https://github.com/thecommcraft/scratchcommunication
Keywords: scratch,api
Classifier: Development Status :: 4 - Beta
Classifier: Intended Audience :: Developers
Classifier: License :: OSI Approved :: MIT License
Classifier: Programming Language :: Python :: 3.11
Classifier: Programming Language :: Python :: 3.12
Classifier: Programming Language :: Python :: 3.13
Requires-Python: >=3.11
License-File: LICENSE
Requires-Dist: requests
Requires-Dist: websocket-client
Requires-Dist: func-timeout
Requires-Dist: pycryptodome
Requires-Dist: attrs
Requires-Dist: browsercookie
Requires-Dist: cryptography
Requires-Dist: super-session-keys
Requires-Dist: weakreflist
Dynamic: author
Dynamic: author-email
Dynamic: classifier
Dynamic: description
Dynamic: description-content-type
Dynamic: keywords
Dynamic: license-file
Dynamic: project-url
Dynamic: requires-dist
Dynamic: requires-python
Dynamic: summary
